pyimgutil/__init__.py
pyimgutil/__main__.py
pyimgutil/arguments.py
pyimgutil/commands.py
pyimgutil-2.1.1.dist-info/LICENSE
pyimgutil-2.1.1.dist-info/METADATA
pyimgutil-2.1.1.dist-info/WHEEL
pyimgutil-2.1.1.dist-info/entry_points.txt
pyimgutil-2.1.1.dist-info/top_level.txt
pyimgutil-2.1.1.dist-info/RECORD
