Metadata-Version: 2.1
Name: pyimgutil
Version: 2.1.1
Summary: A command-line utility for individual or batch image processing.
Home-page: https://gitlab.com/emerac/pyimgutil
Author: emerac
Author-email: 7785766-emerac@users.noreply.gitlab.com
License: GPLv3
Keywords: python,image,photo,utility,processing,convert,crop,resize,rotate,transpose
Platform: UNKNOWN
Classifier: Development Status :: 5 - Production/Stable
Classifier: Intended Audience :: End Users/Desktop
Classifier: License :: OSI Approved :: GNU General Public License v3 or later (GPLv3+)
Classifier: Operating System :: POSIX :: Linux
Classifier: Programming Language :: Python :: 3 :: Only
Classifier: Programming Language :: Python :: 3.9
Classifier: Programming Language :: Python :: 3.8
Classifier: Programming Language :: Python :: 3.7
Classifier: Topic :: Utilities
Requires-Python: >=3.7
License-File: LICENSE
Requires-Dist: Pillow (>=8.1.1)
